arg_cat/__init__.py
arg_cat/arg_cat.py
arg_cat-1.0.4.dist-info/LICENSE
arg_cat-1.0.4.dist-info/METADATA
arg_cat-1.0.4.dist-info/WHEEL
arg_cat-1.0.4.dist-info/top_level.txt
arg_cat-1.0.4.dist-info/RECORD
