Metadata-Version: 2.1
Name: arg_cat
Version: 1.0.4
Summary: Params from arg and environment
Home-page: https://github.com/LunaGao/arg_cat
Author: Luna Gao
Author-email: gao.xue.qi@qq.com
License: UNKNOWN
Project-URL: Bug Tracker, https://github.com/LunaGao/arg_cat/issues
Platform: UNKNOWN
Classifier: Programming Language :: Python :: 3
Classifier: License :: OSI Approved :: MIT License
Classifier: Operating System :: OS Independent
Requires-Python: >=3.6
License-File: LICENSE
